tinyconfig/__init__.py
tinyconfig/base.py
tinyconfig-0.2.0.dist-info/LICENSE
tinyconfig-0.2.0.dist-info/METADATA
tinyconfig-0.2.0.dist-info/WHEEL
tinyconfig-0.2.0.dist-info/RECORD
