Metadata-Version: 2.3
Name: tinyconfig
Version: 0.2.0
Summary: 
License: MIT
Author: Hamlet
Author-email: hamlets849@gmail.com
Requires-Python: >=3.9
Classifier: License :: OSI Approved :: MIT License
Classifier: Programming Language :: Python :: 3
Classifier: Programming Language :: Python :: 3.9
Classifier: Programming Language :: Python :: 3.10
Classifier: Programming Language :: Python :: 3.11
Classifier: Programming Language :: Python :: 3.12
Classifier: Programming Language :: Python :: 3.13
Requires-Dist: pyyaml (>=6.0.2)
Requires-Dist: tomlkit (>=0.13.2)
